agent_connect/__init__.py
agent_connect/agent_description/__init__.py
agent_connect/agent_description/proof.py
agent_connect/anp_crawler/Interface.md
agent_connect/anp_crawler/__init__.py
agent_connect/anp_crawler/anp_client.py
agent_connect/anp_crawler/anp_crawler.py
agent_connect/anp_crawler/anp_interface.py
agent_connect/anp_crawler/anp_parser.py
agent_connect/anp_crawler/readme.md
agent_connect/anp_crawler/test/README.md
agent_connect/anp_crawler/test/__init__.py
agent_connect/anp_crawler/test/example_embedded_openrpc.py
agent_connect/anp_crawler/test/run_tests.py
agent_connect/anp_crawler/test/test_anp_crawler.py
agent_connect/anp_crawler/test/test_data_agent_description.json
agent_connect/anp_crawler/test/test_data_embedded_openrpc.json
agent_connect/anp_crawler/test/test_data_openrpc.json
agent_connect/app_protocols/__init__.py
agent_connect/app_protocols/app_protocols.py
agent_connect/app_protocols/protocol_base/__init__.py
agent_connect/app_protocols/protocol_base/meta_data.json
agent_connect/app_protocols/protocol_base/negotiation_info.json
agent_connect/app_protocols/protocol_base/protocol_documention.md
agent_connect/app_protocols/protocol_base/provider_base.py
agent_connect/app_protocols/protocol_base/provider_description.json
agent_connect/app_protocols/protocol_base/requester_base.py
agent_connect/app_protocols/protocol_base/requester_description.json
agent_connect/app_protocols/protocol_container.py
agent_connect/authentication/__init__.py
agent_connect/authentication/did_wba.py
agent_connect/authentication/did_wba_auth_header.py
agent_connect/authentication/did_wba_verifier.py
agent_connect/authentication/didallclient.py
agent_connect/authentication/verification_methods.py
agent_connect/e2e_encryption/__init__.py
agent_connect/e2e_encryption/message_generation.py
agent_connect/e2e_encryption/short_term_key_generater.py
agent_connect/e2e_encryption/wss_message_client.py
agent_connect/e2e_encryption/wss_message_sdk.py
agent_connect-0.3.6.dist-info/LICENSE
agent_connect-0.3.6.dist-info/METADATA
agent_connect-0.3.6.dist-info/WHEEL
agent_connect-0.3.6.dist-info/RECORD
