Metadata-Version: 2.3
Name: agent-connect
Version: 0.3.6
Summary: An SDK that enables agents to connect with each other, allowing them to perform identity authentication, end-to-end encrypted communication, automatic protocol negotiation based on LLMs, and efficient data exchange.
License: MIT
Author: changshan
Author-email: chgaowei@gmail.com
Requires-Python: >=3.8
Classifier: License :: OSI Approved :: MIT License
Classifier: Operating System :: OS Independent
Classifier: Programming Language :: Python :: 3
Classifier: Programming Language :: Python :: 3.8
Classifier: Programming Language :: Python :: 3.9
Classifier: Programming Language :: Python :: 3.10
Classifier: Programming Language :: Python :: 3.11
Classifier: Programming Language :: Python :: 3.12
Classifier: Programming Language :: Python :: 3.13
Provides-Extra: api
Requires-Dist: aiohttp (>=3.10.10,<4.0.0)
Requires-Dist: asn1crypto (>=1.5.1,<2.0.0)
Requires-Dist: base58 (>=2.1.1,<3.0.0)
Requires-Dist: canonicaljson (>=2.0.0,<3.0.0)
Requires-Dist: cryptography (>=43.0.3,<44.0.0)
Requires-Dist: ecdsa (>=0.19.0,<0.20.0)
Requires-Dist: jcs (>=0.2.1,<0.3.0)
Requires-Dist: jsonschema (>=4.23.0,<5.0.0)
Requires-Dist: pydantic (>=2.9.2,<3.0.0)
Requires-Dist: pyjwt (>=2.9.0,<3.0.0)
Requires-Dist: python-dotenv (>=1.0.1,<2.0.0)
Requires-Dist: requests (>=2.32.3,<3.0.0)
Requires-Dist: websockets (>=13.1,<14.0)
Project-URL: Documentation, https://github.com/agent-network-protocol/AgentNetworkProtocol
Project-URL: Homepage, https://agent-network-protocol.com/
Project-URL: Repository, https://github.com/agent-network-protocol/AgentConnect
